wormgear/__init__.py
wormgear/enums.py
wormgear/calculator/__init__.py
wormgear/calculator/constants.py
wormgear/calculator/core.py
wormgear/calculator/js_bridge.py
wormgear/calculator/json_schema.py
wormgear/calculator/output.py
wormgear/calculator/validation.py
wormgear/cli/__init__.py
wormgear/cli/generate.py
wormgear/core/__init__.py
wormgear/core/bore_sizing.py
wormgear/core/features.py
wormgear/core/globoid_worm.py
wormgear/core/mesh_alignment.py
wormgear/core/rim_thickness.py
wormgear/core/virtual_hobbing.py
wormgear/core/wheel.py
wormgear/core/worm.py
wormgear/io/__init__.py
wormgear/io/loaders.py
wormgear/io/schema.py
wormgear-0.0.22.dist-info/licenses/LICENSE
wormgear-0.0.22.dist-info/METADATA
wormgear-0.0.22.dist-info/WHEEL
wormgear-0.0.22.dist-info/entry_points.txt
wormgear-0.0.22.dist-info/top_level.txt
wormgear-0.0.22.dist-info/RECORD
