Metadata-Version: 2.4
Name: wormgear
Version: 0.0.22
Summary: Unified worm gear calculator and CNC-ready 3D geometry generator
Author-email: Paul Fremantle <paul@fremantle.org>
License: MIT
Project-URL: Homepage, https://wormgear.studio
Project-URL: Documentation, https://github.com/pzfreo/wormgear/blob/main/README.md
Project-URL: Repository, https://github.com/pzfreo/wormgear
Project-URL: Issues, https://github.com/pzfreo/wormgear/issues
Keywords: worm gear,gear calculator,CAD,build123d,CNC,STEP,manufacturing
Classifier: Development Status :: 3 - Alpha
Classifier: Intended Audience :: Manufacturing
Classifier: Intended Audience :: Developers
Classifier: Intended Audience :: Science/Research
Classifier: License :: OSI Approved :: MIT License
Classifier: Programming Language :: Python :: 3
Classifier: Programming Language :: Python :: 3.12
Classifier: Programming Language :: Python :: 3.13
Classifier: Topic :: Scientific/Engineering
Requires-Python: >=3.12
License-File: LICENSE
Requires-Dist: build123d>=0.6.0
Requires-Dist: click>=8.0
Requires-Dist: pydantic<3.0,>=2.0
Provides-Extra: dev
Requires-Dist: pytest>=7.0; extra == "dev"
Requires-Dist: pytest-cov; extra == "dev"
Requires-Dist: black; extra == "dev"
Requires-Dist: ruff; extra == "dev"
Requires-Dist: mypy>=1.0; extra == "dev"
Dynamic: license-file
